<?xml version="1.0" encoding="UTF-8"?>
<flow id="a8683c5e-9f25-4b26-98b8-4c0287e1c560">
  <descriptionCdata><![CDATA[a8683c5e-9f25-4b26-98b8-4c0287e1c560.474ec8ef-7c08-4d8f-9a2b-15d493901470.description=<pre>\nChecks to see if a string matches another string using a specific rule. Input toMatch is the actual string to check to see if it matches the matchTo expression.\n\nInputs\:\n    matchType - The type of match to perform.\nValid values\: Exact Match, Contains, Contains Once, Does Not Contain, Match All Words, Match No Words, Regex\nDefault value\: Exact Match\n    toMatch - The string to check if matches another string.\n    matchTo - The string to match against. \nExamples\: If the matchType is RegEx, the input matchTo is the regular expression like \: ^-?\\d+(([\\.,]\\d+)?)+$. \n    ignoreCase - Boolean value for whether or not to ignore case during match.\nValid values\: False, True\nDefault value\: False\n\nResponses\:\n    success - The String matched.\n    failure - The string did not match, or something went wrong.\n</pre>
a8683c5e-9f25-4b26-98b8-4c0287e1c560.description=<pre>\nThis utility flow is used to determine whether a domain user was provided. It investigates if either of the two inputs has indicated the presence of a domain..\n\nInputs\:\n    adminUsername - The username to search in.\n    domain - The domain to inspect.\n\nResponses\:\n    Is Domain User - The flow identified the presence of a domain in one of the two inputs.\n    Is Not Domai User - The flow did not detect any domain inside the inputs.\n</pre>\n
a8683c5e-9f25-4b26-98b8-4c0287e1c560.f9580192-eff3-488a-9283-44e2020cc41a.description=<pre>\nChecks to see if a string matches another string using a specific rule. Input toMatch is the actual string to check to see if it matches the matchTo expression.\n\nInputs\:\n    matchType - The type of match to perform.\nValid values\: Exact Match, Contains, Contains Once, Does Not Contain, Match All Words, Match No Words, Regex\nDefault value\: Exact Match\n    toMatch - The string to check if matches another string.\n    matchTo - The string to match against. \nExamples\: If the matchType is RegEx, the input matchTo is the regular expression like \: ^-?\\d+(([\\.,]\\d+)?)+$. \n    ignoreCase - Boolean value for whether or not to ignore case during match.\nValid values\: False, True\nDefault value\: False\n\nResponses\:\n    success - The String matched.\n    failure - The string did not match, or something went wrong.\n</pre>
]]></descriptionCdata>
  <annotation>a8683c5e-9f25-4b26-98b8-4c0287e1c560.description</annotation>
  <name>Is Domain User</name>
  <categories/>
  <inputs>
    <userInputBinding id="bec42dd6-b012-4bc9-a9bc-859dd4a0ee37">
      <annotation></annotation>
      <assignFromContext>true</assignFromContext>
      <assignToContext>true</assignToContext>
      <inputType>STRING</inputType>
      <isList>false</isList>
      <required>false</required>
      <isPersisted>true</isPersisted>
      <inputSymbol>adminUsername</inputSymbol>
      <listDelimiter>,</listDelimiter>
      <record>false</record>
      <prompt></prompt>
      <isMultiSelect>false</isMultiSelect>
      <sourceDelimiter>|</sourceDelimiter>
    </userInputBinding>
    <userInputBinding id="dc9eafc6-3405-49e4-98e9-0e14ced26552">
      <annotation></annotation>
      <assignFromContext>true</assignFromContext>
      <assignToContext>true</assignToContext>
      <inputType>STRING</inputType>
      <isList>false</isList>
      <required>false</required>
      <isPersisted>true</isPersisted>
      <inputSymbol>domain</inputSymbol>
      <listDelimiter>,</listDelimiter>
      <record>false</record>
      <prompt></prompt>
      <isMultiSelect>false</isMultiSelect>
      <sourceDelimiter>|</sourceDelimiter>
    </userInputBinding>
  </inputs>
  <possibleResponses>
    <opResponse id="d043b619-ea08-40e5-9100-e3206eeb4fb9">
      <annotation></annotation>
      <name>success</name>
      <isDefault>true</isDefault>
      <onFailure>false</onFailure>
      <type>RESOLVED</type>
      <matchRules/>
    </opResponse>
    <opResponse id="6be4b189-04ed-4770-bab7-23b93f7683c7">
      <annotation></annotation>
      <name>failure</name>
      <isDefault>false</isDefault>
      <onFailure>true</onFailure>
      <type>ERROR</type>
      <matchRules/>
    </opResponse>
  </possibleResponses>
  <availableResultExpressions/>
  <resultExpression id="b4f3b0a8-d830-45a1-a49f-43035a32cd47">
    <annotation></annotation>
    <name>FailureMessage</name>
    <fieldName>FailureMessage</fieldName>
    <sourceType>RAWRESULT</sourceType>
    <filters/>
  </resultExpression>
  <iconSpec id="1e3e4c9d-dbd1-4b66-ab94-27f16bd0372e">
    <baseIcon>flow.png</baseIcon>
    <basePath>System</basePath>
    <readOnly>false</readOnly>
    <layers/>
  </iconSpec>
  <callouts/>
  <checkPointFlow>true</checkPointFlow>
  <compatibleRuntimeContext>false</compatibleRuntimeContext>
  <historyCheckPointFlow>true</historyCheckPointFlow>
  <steps>
    <step id="474ec8ef-7c08-4d8f-9a2b-15d493901470">
      <annotation>a8683c5e-9f25-4b26-98b8-4c0287e1c560.474ec8ef-7c08-4d8f-9a2b-15d493901470.description</annotation>
      <name>Username contains domain character?</name>
      <bounds>
        <x>0.0</x>
        <y>0.0</y>
      </bounds>
      <layer>-1</layer>
      <hideInbound>false</hideInbound>
      <iconSpec id="b91ff1b9-521c-44ed-a3e3-7bb2cb45e062">
        <baseIcon>compare.png</baseIcon>
        <basePath>Utilities</basePath>
        <readOnly>false</readOnly>
        <layers/>
      </iconSpec>
      <addResultToRunContext>false</addResultToRunContext>
      <isCriticalStep>false</isCriticalStep>
      <isNonBlocking>false</isNonBlocking>
      <isParallelStep>false</isParallelStep>
      <isSingleResponse>false</isSingleResponse>
      <recordInHistory>false</recordInHistory>
      <recordRawOutput>true</recordRawOutput>
      <recordPrimaryOutput>true</recordPrimaryOutput>
      <checkPointStep>true</checkPointStep>
      <historyCheckPointStep>true</historyCheckPointStep>
      <scriptResultStep>false</scriptResultStep>
      <userPrompt></userPrompt>
      <bindings>
        <staticBinding id="68612925-564e-470e-8898-4e7b5a7cc61c">
          <annotation></annotation>
          <assignFromContext>false</assignFromContext>
          <assignToContext>false</assignToContext>
          <inputType>STRING</inputType>
          <isList>false</isList>
          <required>true</required>
          <isPersisted>true</isPersisted>
          <inputSymbol>matchType</inputSymbol>
          <listDelimiter>,</listDelimiter>
          <value>Contains Once</value>
          <record>false</record>
        </staticBinding>
        <staticBinding id="336a2b8c-e83b-462e-86cc-f05936028ce7">
          <annotation></annotation>
          <fromContextKey>adminUsername</fromContextKey>
          <assignFromContext>true</assignFromContext>
          <assignToContext>false</assignToContext>
          <inputType>STRING</inputType>
          <isList>false</isList>
          <required>true</required>
          <isPersisted>true</isPersisted>
          <inputSymbol>toMatch</inputSymbol>
          <listDelimiter>,</listDelimiter>
          <value></value>
          <record>false</record>
        </staticBinding>
        <staticBinding id="95beda0f-d24c-4e5b-8bd9-b64bb880dd3c">
          <annotation></annotation>
          <fromContextKey>targetedUsername</fromContextKey>
          <assignFromContext>false</assignFromContext>
          <assignToContext>false</assignToContext>
          <inputType>STRING</inputType>
          <isList>false</isList>
          <required>true</required>
          <isPersisted>true</isPersisted>
          <inputSymbol>matchTo</inputSymbol>
          <listDelimiter>,</listDelimiter>
          <value>\</value>
          <record>false</record>
        </staticBinding>
        <staticBinding id="06444710-fb7b-4f90-9567-e6184486283b">
          <annotation></annotation>
          <assignFromContext>false</assignFromContext>
          <assignToContext>false</assignToContext>
          <inputType>STRING</inputType>
          <isList>false</isList>
          <required>true</required>
          <isPersisted>true</isPersisted>
          <inputSymbol>ignoreCase</inputSymbol>
          <listDelimiter>,</listDelimiter>
          <value>true</value>
          <record>false</record>
        </staticBinding>
      </bindings>
      <transitions>
        <transition id="76213f5c-414b-479c-8ab2-81b8f4053bff">
          <annotation></annotation>
          <name>yes</name>
          <command>NEXT</command>
          <linkMode>false</linkMode>
          <responseSymbol>success</responseSymbol>
          <shouldHandoff>false</shouldHandoff>
          <transitionValue>0.0</transitionValue>
          <destination>
            <refId>41663c24-3562-4178-bf5a-e60a8c0d8ae0</refId>
          </destination>
          <source>
            <refId>474ec8ef-7c08-4d8f-9a2b-15d493901470</refId>
          </source>
          <positions>
            <point>
              <x>50.0</x>
              <y>34.0</y>
            </point>
            <point>
              <x>50.0</x>
              <y>220.0</y>
            </point>
          </positions>
          <labelPosition>
            <x>333.0</x>
            <y>0.0</y>
          </labelPosition>
        </transition>
        <transition id="df6aedf6-4406-4b62-a672-ff846262872e">
          <annotation></annotation>
          <name>no</name>
          <command>NEXT</command>
          <linkMode>false</linkMode>
          <responseSymbol>failure</responseSymbol>
          <shouldHandoff>false</shouldHandoff>
          <transitionValue>0.0</transitionValue>
          <destination>
            <refId>f9580192-eff3-488a-9283-44e2020cc41a</refId>
          </destination>
          <source>
            <refId>474ec8ef-7c08-4d8f-9a2b-15d493901470</refId>
          </source>
          <positions>
            <point>
              <x>50.0</x>
              <y>34.0</y>
            </point>
            <point>
              <x>293.0</x>
              <y>34.0</y>
            </point>
          </positions>
          <labelPosition>
            <x>333.0</x>
            <y>0.0</y>
          </labelPosition>
        </transition>
      </transitions>
      <properties/>
      <opRef>
        <refId>f1dafb35-6463-4a1b-8f87-8aa748497bed</refId>
      </opRef>
      <assignments>
        <flowVariableAssignment id="1a2c003a-1032-4469-b375-b86fc25f42b9">
          <annotation></annotation>
          <name>assignment</name>
          <action>OVERWRITE</action>
          <assignmentTargetType>FLOW_OUTPUT_FIELD</assignmentTargetType>
          <contextKey>exception</contextKey>
          <expression id="ac45cac1-1557-4a4e-adf4-0e273fcabf48">
            <annotation></annotation>
            <name>Result Field: exception</name>
            <fieldName>exception</fieldName>
            <sourceType>RAWRESULT</sourceType>
            <filters/>
          </expression>
        </flowVariableAssignment>
        <flowVariableAssignment id="1b973ef2-4627-467e-9978-a935b35cb5a1">
          <annotation></annotation>
          <name>assignment</name>
          <action>OVERWRITE</action>
          <assignmentTargetType>FLOW_OUTPUT_FIELD</assignmentTargetType>
          <contextKey>returnResult</contextKey>
          <expression id="b4e2aa53-0ee6-490e-8918-b1add4511dd3">
            <annotation></annotation>
            <name>Result Field: returnResult</name>
            <fieldName>returnResult</fieldName>
            <sourceType>RAWRESULT</sourceType>
            <filters/>
          </expression>
        </flowVariableAssignment>
      </assignments>
      <throttleSize>0</throttleSize>
    </step>
    <returnStep id="b840e09a-ddee-4184-9ff1-4c7d48707e12">
      <annotation></annotation>
      <name>Is Not Domain User</name>
      <bounds>
        <x>246.0</x>
        <y>190.0</y>
      </bounds>
      <layer>-1</layer>
      <hideInbound>false</hideInbound>
      <addResultToRunContext>false</addResultToRunContext>
      <isCriticalStep>false</isCriticalStep>
      <isNonBlocking>false</isNonBlocking>
      <isParallelStep>false</isParallelStep>
      <isSingleResponse>false</isSingleResponse>
      <recordInHistory>false</recordInHistory>
      <recordRawOutput>true</recordRawOutput>
      <recordPrimaryOutput>true</recordPrimaryOutput>
      <checkPointStep>true</checkPointStep>
      <historyCheckPointStep>true</historyCheckPointStep>
      <scriptResultStep>false</scriptResultStep>
      <userPrompt></userPrompt>
      <bindings/>
      <transitions>
        <transition id="4eb1a6ef-135d-46be-a79a-b6758e2de0f2">
          <annotation></annotation>
          <name>return</name>
          <command>NEXT</command>
          <linkMode>false</linkMode>
          <responseSymbol>failure</responseSymbol>
          <shouldHandoff>false</shouldHandoff>
          <transitionValue>0.0</transitionValue>
          <destination>
            <refId>b840e09a-ddee-4184-9ff1-4c7d48707e12</refId>
          </destination>
          <source>
            <refId>b840e09a-ddee-4184-9ff1-4c7d48707e12</refId>
          </source>
          <positions/>
        </transition>
      </transitions>
      <properties/>
      <returnStepType>ERROR</returnStepType>
      <assignments/>
    </returnStep>
    <returnStep id="41663c24-3562-4178-bf5a-e60a8c0d8ae0">
      <annotation></annotation>
      <name>Is Domain User</name>
      <bounds>
        <x>0.0</x>
        <y>186.0</y>
      </bounds>
      <layer>-1</layer>
      <hideInbound>false</hideInbound>
      <addResultToRunContext>false</addResultToRunContext>
      <isCriticalStep>false</isCriticalStep>
      <isNonBlocking>false</isNonBlocking>
      <isParallelStep>false</isParallelStep>
      <isSingleResponse>false</isSingleResponse>
      <recordInHistory>false</recordInHistory>
      <recordRawOutput>true</recordRawOutput>
      <recordPrimaryOutput>true</recordPrimaryOutput>
      <checkPointStep>true</checkPointStep>
      <historyCheckPointStep>true</historyCheckPointStep>
      <scriptResultStep>false</scriptResultStep>
      <userPrompt></userPrompt>
      <bindings/>
      <transitions>
        <transition id="716255e0-b43f-468b-9201-322602a130d9">
          <annotation></annotation>
          <name>return</name>
          <command>NEXT</command>
          <linkMode>false</linkMode>
          <responseSymbol>success</responseSymbol>
          <shouldHandoff>false</shouldHandoff>
          <transitionValue>0.0</transitionValue>
          <destination>
            <refId>41663c24-3562-4178-bf5a-e60a8c0d8ae0</refId>
          </destination>
          <source>
            <refId>41663c24-3562-4178-bf5a-e60a8c0d8ae0</refId>
          </source>
          <positions/>
        </transition>
      </transitions>
      <properties/>
      <returnStepType>RESOLVED</returnStepType>
      <assignments/>
    </returnStep>
    <step id="f9580192-eff3-488a-9283-44e2020cc41a">
      <annotation>a8683c5e-9f25-4b26-98b8-4c0287e1c560.f9580192-eff3-488a-9283-44e2020cc41a.description</annotation>
      <name>Is Domain Empty?</name>
      <bounds>
        <x>243.0</x>
        <y>0.0</y>
      </bounds>
      <layer>-1</layer>
      <hideInbound>false</hideInbound>
      <iconSpec id="9e7627dd-ae95-478c-933a-07e6bf9cd2af">
        <baseIcon>compare.png</baseIcon>
        <basePath>Utilities</basePath>
        <readOnly>false</readOnly>
        <layers/>
      </iconSpec>
      <addResultToRunContext>false</addResultToRunContext>
      <isCriticalStep>false</isCriticalStep>
      <isNonBlocking>false</isNonBlocking>
      <isParallelStep>false</isParallelStep>
      <isSingleResponse>false</isSingleResponse>
      <recordInHistory>false</recordInHistory>
      <recordRawOutput>true</recordRawOutput>
      <recordPrimaryOutput>true</recordPrimaryOutput>
      <checkPointStep>true</checkPointStep>
      <historyCheckPointStep>true</historyCheckPointStep>
      <scriptResultStep>false</scriptResultStep>
      <userPrompt></userPrompt>
      <bindings>
        <staticBinding id="1b459283-70d3-445c-bc2d-d4539e3e2f9d">
          <annotation></annotation>
          <assignFromContext>false</assignFromContext>
          <assignToContext>false</assignToContext>
          <inputType>STRING</inputType>
          <isList>false</isList>
          <required>true</required>
          <isPersisted>true</isPersisted>
          <inputSymbol>matchType</inputSymbol>
          <listDelimiter>,</listDelimiter>
          <value>Exact Match</value>
          <record>false</record>
        </staticBinding>
        <staticBinding id="2dc713fe-2416-4b13-91b7-c63bd88c169d">
          <annotation></annotation>
          <fromContextKey>domain</fromContextKey>
          <assignFromContext>true</assignFromContext>
          <assignToContext>false</assignToContext>
          <inputType>STRING</inputType>
          <isList>false</isList>
          <required>true</required>
          <isPersisted>true</isPersisted>
          <inputSymbol>toMatch</inputSymbol>
          <listDelimiter>,</listDelimiter>
          <value></value>
          <record>false</record>
        </staticBinding>
        <staticBinding id="9b46cf1a-212a-403d-a303-1a4b29481dd8">
          <annotation></annotation>
          <fromContextKey>domain</fromContextKey>
          <assignFromContext>false</assignFromContext>
          <assignToContext>false</assignToContext>
          <inputType>STRING</inputType>
          <isList>false</isList>
          <required>true</required>
          <isPersisted>true</isPersisted>
          <inputSymbol>matchTo</inputSymbol>
          <listDelimiter>,</listDelimiter>
          <value></value>
          <record>false</record>
        </staticBinding>
        <staticBinding id="0447b8a7-5ee2-4ca8-8447-8eb4037442fe">
          <annotation></annotation>
          <assignFromContext>false</assignFromContext>
          <assignToContext>false</assignToContext>
          <inputType>STRING</inputType>
          <isList>false</isList>
          <required>true</required>
          <isPersisted>true</isPersisted>
          <inputSymbol>ignoreCase</inputSymbol>
          <listDelimiter>,</listDelimiter>
          <value>true</value>
          <record>false</record>
        </staticBinding>
      </bindings>
      <transitions>
        <transition id="e2463f54-6b61-433f-88bc-8140d2245e6a">
          <annotation></annotation>
          <name>not empty</name>
          <command>NEXT</command>
          <linkMode>false</linkMode>
          <responseSymbol>failure</responseSymbol>
          <shouldHandoff>false</shouldHandoff>
          <transitionValue>0.0</transitionValue>
          <destination>
            <refId>41663c24-3562-4178-bf5a-e60a8c0d8ae0</refId>
          </destination>
          <source>
            <refId>f9580192-eff3-488a-9283-44e2020cc41a</refId>
          </source>
          <positions>
            <point>
              <x>293.0</x>
              <y>34.0</y>
            </point>
            <point>
              <x>50.0</x>
              <y>220.0</y>
            </point>
          </positions>
          <labelPosition>
            <x>333.0</x>
            <y>0.0</y>
          </labelPosition>
        </transition>
        <transition id="61f5c62b-cd48-40f8-9ab3-cb65f4789b6f">
          <annotation></annotation>
          <name>empty</name>
          <command>NEXT</command>
          <linkMode>false</linkMode>
          <responseSymbol>success</responseSymbol>
          <shouldHandoff>false</shouldHandoff>
          <transitionValue>0.0</transitionValue>
          <destination>
            <refId>b840e09a-ddee-4184-9ff1-4c7d48707e12</refId>
          </destination>
          <source>
            <refId>f9580192-eff3-488a-9283-44e2020cc41a</refId>
          </source>
          <positions>
            <point>
              <x>293.0</x>
              <y>34.0</y>
            </point>
            <point>
              <x>296.0</x>
              <y>224.0</y>
            </point>
          </positions>
          <labelPosition>
            <x>333.0</x>
            <y>0.0</y>
          </labelPosition>
        </transition>
      </transitions>
      <properties/>
      <opRef>
        <refId>f1dafb35-6463-4a1b-8f87-8aa748497bed</refId>
      </opRef>
      <assignments>
        <flowVariableAssignment id="dfa7ef12-26ec-4c2d-9dca-6b533e4e57ce">
          <annotation></annotation>
          <name>assignment</name>
          <action>OVERWRITE</action>
          <assignmentTargetType>FLOW_OUTPUT_FIELD</assignmentTargetType>
          <contextKey>exception</contextKey>
          <expression id="41764184-62b3-4c79-94f9-130257d9a5f5">
            <annotation></annotation>
            <name>Result Field: exception</name>
            <fieldName>exception</fieldName>
            <sourceType>RAWRESULT</sourceType>
            <filters/>
          </expression>
        </flowVariableAssignment>
        <flowVariableAssignment id="eda05c57-cfd9-4666-adca-6866c1e833c0">
          <annotation></annotation>
          <name>assignment</name>
          <action>OVERWRITE</action>
          <assignmentTargetType>FLOW_OUTPUT_FIELD</assignmentTargetType>
          <contextKey>returnResult</contextKey>
          <expression id="6d2a8f9a-99fc-4639-a1b0-7504216acd19">
            <annotation></annotation>
            <name>Result Field: returnResult</name>
            <fieldName>returnResult</fieldName>
            <sourceType>RAWRESULT</sourceType>
            <filters/>
          </expression>
        </flowVariableAssignment>
      </assignments>
      <throttleSize>0</throttleSize>
    </step>
  </steps>
  <startSteps>474ec8ef-7c08-4d8f-9a2b-15d493901470</startSteps>
</flow>